multilayer_hurnet/__init__.py
multilayer_hurnet/multilayer_hurnet.py
multilayer_hurnet-1.0.4.dist-info/LICENSE.txt
multilayer_hurnet-1.0.4.dist-info/METADATA
multilayer_hurnet-1.0.4.dist-info/WHEEL
multilayer_hurnet-1.0.4.dist-info/top_level.txt
multilayer_hurnet-1.0.4.dist-info/RECORD
