Metadata-Version: 2.1
Name: multilayer-hurnet
Version: 1.0.4
Home-page: https://github.com/
Author: SAPIENS TECHNOLOGY
License: Proprietary Software
License-File: LICENSE.txt
Requires-Dist: numpy
